{"quirkle":[{"match":9,"round":1,"name":"Co","value":6},{"match":9,"round":1,"name":"Lu","value":2},{"match":9,"round":1,"name":"Cr","value":3},{"match":9,"round":1,"name":"Na","value":4},{"match":9,"round":2,"name":"Co","value":3},{"match":9,"round":2,"name":"Lu","value":3},{"match":9,"round":2,"name":"Cr","value":3},{"match":9,"round":2,"name":"Na","value":6},{"match":9,"round":3,"name":"Co","value":3},{"match":9,"round":3,"name":"Lu","value":4},{"match":9,"round":3,"name":"Cr","value":4},{"match":9,"round":3,"name":"Na","value":7},{"match":9,"round":4,"name":"Co","value":3},{"match":9,"round":4,"name":"Lu","value":5},{"match":9,"round":4,"name":"Cr","value":4},{"match":9,"round":4,"name":"Na","value":5},{"match":9,"round":5,"name":"Co","value":5},{"match":9,"round":5,"name":"Lu","value":5},{"match":9,"round":5,"name":"Cr","value":4},{"match":9,"round":5,"name":"Na","value":5},{"match":9,"round":6,"name":"Co","value":3},{"match":9,"round":6,"name":"Lu","value":6},{"match":9,"round":6,"name":"Cr","value":5},{"match":9,"round":6,"name":"Na","value":4},{"match":9,"round":7,"name":"Co","value":3},{"match":9,"round":7,"name":"Lu","value":7},{"match":9,"round":7,"name":"Cr","value":12},{"match":9,"round":7,"name":"Na","value":5},{"match":9,"round":8,"name":"Co","value":6},{"match":9,"round":8,"name":"Lu","value":12},{"match":9,"round":8,"name":"Cr","value":12},{"match":9,"round":8,"name":"Na","value":5},{"match":9,"round":9,"name":"Co","value":12},{"match":9,"round":9,"name":"Lu","value":5},{"match":9,"round":9,"name":"Cr","value":12},{"match":9,"round":9,"name":"Na","value":12},{"match":9,"round":10,"name":"Co","value":3},{"match":9,"round":10,"name":"Lu","value":3},{"match":9,"round":10,"name":"Cr","value":4},{"match":9,"round":10,"name":"Na","value":5},{"match":9,"round":11,"name":"Co","value":3},{"match":9,"round":11,"name":"Lu","value":7},{"match":9,"round":11,"name":"Cr","value":5},{"match":9,"round":11,"name":"Na","value":12},{"match":9,"round":12,"name":"Co","value":5},{"match":9,"round":12,"name":"Lu","value":5},{"match":9,"round":12,"name":"Cr","value":4},{"match":9,"round":12,"name":"Na","value":12},{"match":9,"round":13,"name":"Co","value":4},{"match":9,"round":13,"name":"Lu","value":12},{"match":9,"round":13,"name":"Cr","value":5},{"match":9,"round":13,"name":"Na","value":12},{"match":9,"round":14,"name":"Co","value":5},{"match":9,"round":14,"name":"Lu","value":6},{"match":9,"round":14,"name":"Cr","value":5},{"match":9,"round":14,"name":"Na","value":12},{"match":9,"round":15,"name":"Co","value":12},{"match":9,"round":15,"name":"Lu","value":11},{"match":9,"round":15,"name":"Cr","value":4},{"match":9,"round":15,"name":"Na","value":8}],"totals":[{"match":9,"name":"Co","score":76},{"match":9,"name":"Lu","score":93},{"match":9,"name":"Cr","score":86},{"match":9,"name":"Na","score":114},{"match":10,"name":"Co","score":86},{"match":10,"name":"Lu","score":97},{"match":10,"name":"Cr","score":119},{"match":10,"name":"Na","score":135},{"match":11,"name":"Co","score":86},{"match":11,"name":"Lu","score":130},{"match":11,"name":"Cr","score":99},{"match":11,"name":"Na","score":129},{"match":12,"name":"Co","score":111},{"match":12,"name":"Lu","score":95},{"match":12,"name":"Cr","score":87},{"match":12,"name":"Na","score":142},{"match":13,"name":"Co","score":85},{"match":13,"name":"Lu","score":91},{"match":13,"name":"Cr","score":128},{"match":13,"name":"Na","score":96},{"match":14,"name":"Co","score":124},{"match":14,"name":"Lu","score":128},{"match":14,"name":"Cr","score":119},{"match":14,"name":"Na","score":125},{"match":15,"name":"Co","score":83},{"match":15,"name":"Lu","score":108},{"match":15,"name":"Cr","score":81},{"match":15,"name":"Na","score":132},{"match":16,"name":"Co","score":94},{"match":16,"name":"Lu","score":137},{"match":16,"name":"Cr","score":134},{"match":16,"name":"Na","score":114},{"match":17,"name":"Co","score":88},{"match":17,"name":"Lu","score":118},{"match":17,"name":"Cr","score":141},{"match":17,"name":"Na","score":129},{"match":18,"name":"Co","score":109},{"match":18,"name":"Lu","score":104},{"match":18,"name":"Cr","score":126},{"match":18,"name":"Na","score":125},{"match":19,"name":"Co","score":103},{"match":19,"name":"Lu","score":130},{"match":19,"name":"Cr","score":107},{"match":19,"name":"Na","score":112}]}
